{"expireTime":9007200798579517000,"key":"transformer-remark-markdown-ast-e08014541ff61f8f77255ab8532bac77--","val":{"type":"root","children":[{"type":"paragraph","children":[{"type":"text","value":"This is my very third blog post in Gatsby","position":{"start":{"line":2,"column":1,"offset":1},"end":{"line":2,"column":42,"offset":42},"indent":[]}}],"position":{"start":{"line":2,"column":1,"offset":1},"end":{"line":2,"column":42,"offset":42},"indent":[]}}],"position":{"start":{"line":1,"column":1,"offset":0},"end":{"line":2,"column":42,"offset":42}}}}